crosspress/__init__.py
crosspress/_darwin.py
crosspress/_linux.py
crosspress/_windows.py
crosspress/cli.py
crosspress/dict.py
crosspress-0.3.0.dist-info/METADATA
crosspress-0.3.0.dist-info/WHEEL
crosspress-0.3.0.dist-info/entry_points.txt
crosspress-0.3.0.dist-info/top_level.txt
crosspress-0.3.0.dist-info/RECORD
