Metadata-Version: 2.1
Name: crosspress
Version: 0.3.0
Summary: Cross-platform lightweight keyboard simulator
Home-page: https://gitlab.com/Vadimhtml/crosspress
Author: Vadimhtml
Author-email: i@vadimhtml.ru
License: MIT
Keywords: keyboard simulator Windows Linux macOS
Platform: UNKNOWN
Classifier: Development Status :: 3 - Alpha
Classifier: License :: OSI Approved :: MIT License
Classifier: Operating System :: Microsoft :: Windows
Classifier: Operating System :: POSIX :: Linux
Classifier: Operating System :: Unix
Classifier: Operating System :: MacOS :: MacOS X
Classifier: Programming Language :: Python :: 3
Classifier: Topic :: Software Development :: Libraries :: Python Modules
Classifier: Topic :: Utilities
Requires-Dist: pyobjc-framework-Quartz ; sys_platform == "darwin"
